{
  "validator_burn_percentage": 0.0,
  "environments": {
    "GAME": {
      "enabled_for_sampling": true,
      "enabled_for_scoring": true,
      "sampling_config": {
        "dataset_range": [[0, 500000000],[600000000, 800000000]],
        "sampling_count": 50,
        "rotation_enabled": true,
        "rotation_count": 1,
        "rotation_interval": 170
      }
    },
    "SWE-INFINITE": {
      "display_name": "SWE",
      "enabled_for_sampling": true,
      "enabled_for_scoring": true,
      "sampling_config": {
        "dataset_range": [[1616, 1716]],
        "dataset_range_source": {
          "url": "https://pub-7882418a56434a479bf9a7febd660b36.r2.dev/bugs/metadata.json",
          "field": "tasks.completed_up_to",
          "range_type": "zero_to_value"
        },
        "sampling_count": 40,
        "rotation_enabled": true,
        "rotation_count": 1,
        "rotation_interval": 260
      }
    },
    "LIVEWEB": {
      "enabled_for_sampling": true,
      "enabled_for_scoring": true,
      "sampling_config": {
        "dataset_range": [[0, 78060000]],
        "sampling_count": 50,
        "rotation_enabled": true,
        "rotation_count": 1,
        "rotation_interval": 170
      }
    },
    "LOGPROBS": {
      "enabled_for_sampling": true,
      "enabled_for_scoring": false,
      "sampling_config": {
        "dataset_range": [[100000000, 400000000]],
        "sampling_count": 50,
        "rotation_enabled": true,
        "rotation_count": 1,
        "rotation_interval": 21600
      }
    },
    "NAVWORLD": {
      "enabled_for_sampling": true,
      "enabled_for_scoring": true,
      "sampling_config": {
        "dataset_range": [[0, 1000000000]],
        "sampling_count": 50,
        "rotation_enabled": true,
        "rotation_count": 1,
        "rotation_interval": 170
      }
    },
    "MEMORY": {
      "enabled_for_sampling": true,
      "enabled_for_scoring": true,
      "sampling_config": {
        "dataset_range": [[0, 1000000000]],
        "sampling_count": 40,
        "rotation_enabled": true,
        "rotation_count": 1,
        "rotation_interval": 220
      }
    },
    "DISTILL": {
      "enabled_for_sampling": true,
      "enabled_for_scoring": true,
      "sampling_config": {
        "dataset_range": [[30, 110]],
        "dataset_range_source": {
          "url": "https://pub-4546777cb27840ec91b892f19eb5742b.r2.dev/metadata.json",
          "field": "completed_up_to",
          "range_type": "zero_to_value"
        },
        "sampling_count": 30,
        "rotation_enabled": true,
        "rotation_count": 1,
        "rotation_interval": 290
      }
    }
  }
}
